fog/__init__.py
fog/buildtools/__init__.py
fog/buildtools/buildtools.py
fog/buildtools/changelog.py
fog/buildtools/version.py
fog_buildtools-1.0.2.dist-info/licenses/LICENSE
fog_buildtools-1.0.2.dist-info/METADATA
fog_buildtools-1.0.2.dist-info/WHEEL
fog_buildtools-1.0.2.dist-info/top_level.txt
fog_buildtools-1.0.2.dist-info/RECORD
