Metadata-Version: 2.4
Name: fog.buildtools
Version: 1.0.2
Summary: Build tools for GOG Galaxy 2.0 plugins
Author: FriendsOfGalaxy
Author-email: FriendsOfGalaxy@gmail.com
License: MIT
Classifier: Development Status :: 4 - Beta
Classifier: Intended Audience :: Developers
Classifier: Topic :: Software Development :: Build Tools
Classifier: License :: OSI Approved :: MIT License
Classifier: Programming Language :: Python :: 3
Requires-Python: >=3.6
License-File: LICENSE
Requires-Dist: pip~=25.2
Requires-Dist: pip-tools~=7.5
Dynamic: author
Dynamic: author-email
Dynamic: classifier
Dynamic: description
Dynamic: description-content-type
Dynamic: license
Dynamic: license-file
Dynamic: requires-dist
Dynamic: requires-python
Dynamic: summary
